gora/__init__.py
gora/inline.py
gora/main-contract.json
gora-0.0.8.dist-info/LICENSE
gora-0.0.8.dist-info/METADATA
gora-0.0.8.dist-info/WHEEL
gora-0.0.8.dist-info/top_level.txt
gora-0.0.8.dist-info/RECORD
