Metadata-Version: 2.1
Name: gora
Version: 0.0.8
Summary: Gora Decentralized Oracle utility functions
Author-email: Gora <communications@gora.io>
Project-URL: Homepage, https://gora.io/
Project-URL: Gora, https://github.com/GoraNetwork/pygora
Keywords: gora,algorand,blockchain oracle,blockchain
Classifier: Programming Language :: Python :: 3
Classifier: License :: OSI Approved :: MIT License
Classifier: Operating System :: POSIX :: Linux
Requires-Python: >=3.10
License-File: LICENSE
Requires-Dist: beaker-pyteal
